anti_sentinel/__init__.py
anti_sentinel/cli.py
anti_sentinel/config.py
anti_sentinel/container.py
anti_sentinel/core.py
anti_sentinel/interfaces.py
anti_sentinel/tools.py
anti_sentinel/worker.py
anti_sentinel/adapters/__init__.py
anti_sentinel/adapters/memory_adapter.py
anti_sentinel/adapters/openai_adapter.py
anti_sentinel/agents/__init__.py
anti_sentinel/agents/base.py
anti_sentinel/agents/writer.py
anti_sentinel/http/__init__.py
anti_sentinel/http/app_factory.py
anti_sentinel/http/controllers.py
anti_sentinel/http/dashboard.py
anti_sentinel/http/middleware.py
anti_sentinel/http/router.py
anti_sentinel/services/__init__.py
anti_sentinel/services/metrics.py
anti_sentinel/services/queue.py
anti_sentinel/static/__init__.py
anti_sentinel/static/docs/404.html
anti_sentinel/static/docs/index.html
anti_sentinel/static/docs/objects.inv
anti_sentinel/static/docs/sitemap.xml
anti_sentinel/static/docs/sitemap.xml.gz
anti_sentinel/static/docs/assets/_mkdocstrings.css
anti_sentinel/static/docs/assets/images/favicon.png
anti_sentinel/static/docs/assets/javascripts/bundle.79ae519e.min.js
anti_sentinel/static/docs/assets/javascripts/bundle.79ae519e.min.js.map
anti_sentinel/static/docs/assets/javascripts/lunr/tinyseg.js
anti_sentinel/static/docs/assets/javascripts/lunr/wordcut.js
anti_sentinel/static/docs/assets/javascripts/lunr/min/lunr.ar.min.js
anti_sentinel/static/docs/assets/javascripts/lunr/min/lunr.da.min.js
anti_sentinel/static/docs/assets/javascripts/lunr/min/lunr.de.min.js
anti_sentinel/static/docs/assets/javascripts/lunr/min/lunr.du.min.js
anti_sentinel/static/docs/assets/javascripts/lunr/min/lunr.el.min.js
anti_sentinel/static/docs/assets/javascripts/lunr/min/lunr.es.min.js
anti_sentinel/static/docs/assets/javascripts/lunr/min/lunr.fi.min.js
anti_sentinel/static/docs/assets/javascripts/lunr/min/lunr.fr.min.js
anti_sentinel/static/docs/assets/javascripts/lunr/min/lunr.he.min.js
anti_sentinel/static/docs/assets/javascripts/lunr/min/lunr.hi.min.js
anti_sentinel-0.1.2.dist-info/licenses/LICENSE
anti_sentinel-0.1.2.dist-info/METADATA
anti_sentinel-0.1.2.dist-info/WHEEL
anti_sentinel-0.1.2.dist-info/entry_points.txt
anti_sentinel-0.1.2.dist-info/top_level.txt
anti_sentinel-0.1.2.dist-info/RECORD
