Metadata-Version: 2.4
Name: anti_sentinel
Version: 0.1.2
License-File: LICENSE
Requires-Dist: typer
Requires-Dist: rich
Requires-Dist: fastapi
Requires-Dist: uvicorn
Requires-Dist: openai
Requires-Dist: pyyaml
Requires-Dist: python-dotenv
Requires-Dist: mem0ai
Requires-Dist: qdrant-client
Requires-Dist: google-genai
Requires-Dist: jinja2
Requires-Dist: aiosqlite
Requires-Dist: mkdocs
Requires-Dist: mkdocs-material
Requires-Dist: mkdocstrings[python]
Dynamic: description
Dynamic: description-content-type
Dynamic: license-file
Dynamic: requires-dist
